imger
