Metadata-Version: 1.1
Name: django-imger
Version: 0.2.3
Summary: A Django app that ties into django's admin and allows client side resizing and placement of images.
Home-page: https://github.com/4shaw/django-imger
Author: Brett Shaw
Author-email: b4shaw@gamil.com
License: BSD License
Platform: UNKNOWN
Classifier: Environment :: Web Environment
Classifier: Framework :: Django
Classifier: Intended Audience :: Developers
Classifier: License :: OSI Approved :: BSD License
Classifier: Operating System :: OS Independent
Classifier: Programming Language :: Python
Classifier: Topic :: Internet :: WWW/HTTP
Classifier: Topic :: Internet :: WWW/HTTP :: Dynamic Content
